hvae_backbone/__init__.py
hvae_backbone/analysis.py
hvae_backbone/analysis_tools.py
hvae_backbone/analyze.py
hvae_backbone/block.py
hvae_backbone/checkpoint.py
hvae_backbone/functional.py
hvae_backbone/hvae.py
hvae_backbone/sequence.py
hvae_backbone/utils.py
hvae_backbone/elements/__init__.py
hvae_backbone/elements/data_preproc.py
hvae_backbone/elements/dataset.py
hvae_backbone/elements/distributions.py
hvae_backbone/elements/layers.py
hvae_backbone/elements/losses.py
hvae_backbone/elements/nets.py
hvae_backbone/elements/optimizers.py
hvae_backbone/elements/schedules.py
hvae_backbone-0.1.126.dist-info/LICENSE
hvae_backbone-0.1.126.dist-info/METADATA
hvae_backbone-0.1.126.dist-info/WHEEL
hvae_backbone-0.1.126.dist-info/top_level.txt
hvae_backbone-0.1.126.dist-info/RECORD
